LICENSE
MANIFEST.in
run
run.py
setup.py
aarddict/__init__.py
aarddict/aar.css.tmpl
aarddict/aar.js
aarddict/debug.py
aarddict/dictionary.py
aarddict/external.png
aarddict/mediawiki_monobook.css
aarddict/mediawiki_shared.css
aarddict/qtui.py
aarddict/res.py
aarddict/shared.css
aarddict/state.py
aarddict/timef.py
aarddict.egg-info/PKG-INFO
aarddict.egg-info/SOURCES.txt
aarddict.egg-info/dependency_links.txt
aarddict.egg-info/entry_points.txt
aarddict.egg-info/requires.txt
aarddict.egg-info/top_level.txt
aarddict/icons/Human-O2/16x16/actions/add-files-to-archive.png
aarddict/icons/Human-O2/16x16/actions/add-folder-to-archive.png
aarddict/icons/Human-O2/16x16/actions/application-exit.png
aarddict/icons/Human-O2/16x16/actions/document-open-recent.png
aarddict/icons/Human-O2/16x16/actions/document-properties.png
aarddict/icons/Human-O2/16x16/actions/document-save.png
aarddict/icons/Human-O2/16x16/actions/edit-clear.png
aarddict/icons/Human-O2/16x16/actions/edit-copy.png
aarddict/icons/Human-O2/16x16/actions/edit-cut.png
aarddict/icons/Human-O2/16x16/actions/edit-delete.png
aarddict/icons/Human-O2/16x16/actions/edit-find.png
aarddict/icons/Human-O2/16x16/actions/edit-paste.png
aarddict/icons/Human-O2/16x16/actions/edit-select-all.png
aarddict/icons/Human-O2/16x16/actions/go-next-page.png
aarddict/icons/Human-O2/16x16/actions/go-next.png
aarddict/icons/Human-O2/16x16/actions/go-previous-page.png
aarddict/icons/Human-O2/16x16/actions/go-previous.png
aarddict/icons/Human-O2/16x16/actions/help-about.png
aarddict/icons/Human-O2/16x16/actions/list-remove.png
aarddict/icons/Human-O2/16x16/actions/system-run.png
aarddict/icons/Human-O2/16x16/actions/system-search.png
aarddict/icons/Human-O2/16x16/actions/view-fullscreen.png
aarddict/icons/Human-O2/16x16/actions/view-restore.png
aarddict/icons/Human-O2/16x16/actions/window-close.png
aarddict/icons/Human-O2/16x16/actions/zoom-in.png
aarddict/icons/Human-O2/16x16/actions/zoom-original.png
aarddict/icons/Human-O2/16x16/actions/zoom-out.png
aarddict/icons/Human-O2/16x16/emblems/emblem-art2.png
aarddict/icons/Human-O2/16x16/emblems/emblem-ok.png
aarddict/icons/Human-O2/16x16/emblems/emblem-unreadable.png
