Metadata-Version: 1.0
Name: aarddict
Version: 0.9.3
Summary: Aard Dictionary is a multiplatform dictionary and offline Wikipedia reader.
Home-page: http://aarddict.org
Author: Igor Tkach
Author-email: itkach@aarddict.org
License: GPL 3
Keywords: aarddict,dict,dictionary,maemo,netbook
Platform: UNKNOWN
Classifier: Development Status :: 4 - Beta
Classifier: Operating System :: OS Independent
Classifier: Programming Language :: Python
Classifier: License :: OSI Approved :: GNU General Public License (GPL)
Classifier: Topic :: Utilities
Classifier: Environment :: X11 Applications :: Qt
